MANIFEST.in
README.rst
requirements.txt
requirements_dev.txt
requirements_stable.txt
setup.py
lino_openui5/__init__.py
lino_openui5/setup_info.py
lino_openui5.egg-info/PKG-INFO
lino_openui5.egg-info/SOURCES.txt
lino_openui5.egg-info/dependency_links.txt
lino_openui5.egg-info/not-zip-safe
lino_openui5.egg-info/requires.txt
lino_openui5.egg-info/top_level.txt
lino_openui5/openui5/__init__.py
lino_openui5/openui5/models.py
lino_openui5/openui5/renderer.py
lino_openui5/openui5/views.py
lino_openui5/openui5/config/openui5/main.html
lino_openui5/openui5/config/openui5/controller/App.controller.js
lino_openui5/openui5/config/openui5/controller/HelloDialog.js
lino_openui5/openui5/config/openui5/controller/HelloPanel.controller.js
lino_openui5/openui5/config/openui5/controller/SideNav.controller.js
lino_openui5/openui5/config/openui5/controller/baseController.js
lino_openui5/openui5/config/openui5/controller/dashboard.controller.js
lino_openui5/openui5/config/openui5/controller/detail.controller.js
lino_openui5/openui5/config/openui5/controller/fragment.controller.js
lino_openui5/openui5/config/openui5/controller/mtable.controller.js
lino_openui5/openui5/config/openui5/controller/table.controller.js
lino_openui5/openui5/config/openui5/core/Component.js
lino_openui5/openui5/config/openui5/core/manifest.json
lino_openui5/openui5/config/openui5/elems/column/DisplayElement.xml
lino_openui5/openui5/config/openui5/elems/column/FieldElement.xml
lino_openui5/openui5/config/openui5/elems/column/TableColumn.xml
lino_openui5/openui5/config/openui5/elems/field/CheckBoxFieldElement.xml
lino_openui5/openui5/config/openui5/elems/field/ChoiceListFieldElement.xml
lino_openui5/openui5/config/openui5/elems/field/ComboElement.xml
lino_openui5/openui5/config/openui5/elems/field/DateFieldElement.xml
lino_openui5/openui5/config/openui5/elems/field/DateTimeFieldElement.xml
lino_openui5/openui5/config/openui5/elems/field/DetailMainPanel.xml
lino_openui5/openui5/config/openui5/elems/field/DisplayElement.xml
lino_openui5/openui5/config/openui5/elems/field/FieldElement.xml
lino_openui5/openui5/config/openui5/elems/field/ForeignKeyElement.xml
lino_openui5/openui5/config/openui5/elems/field/GridElement.xml
