Metadata-Version: 1.1
Name: lino-openui5
Version: 20.8.2
Summary: The SAP Open Ui5 user interface for Lino
Home-page: http://www.lino-framework.org
Author: Luc Saffre
Author-email: luc.saffre@gmail.com
License: BSD-2-Clause
Platform: UNKNOWN
Classifier:   Programming Language :: Python
Classifier:   Programming Language :: Python :: 3
Classifier:   Development Status :: 1 - Planning
Classifier:   Environment :: Web Environment
Classifier:   Framework :: Django
Classifier:   Intended Audience :: Developers
Classifier:   Intended Audience :: System Administrators
Classifier:   License :: OSI Approved :: BSD License
Classifier:   Natural Language :: English
Classifier:   Operating System :: OS Independent
Classifier:   Topic :: Database :: Front-Ends
Classifier:   Topic :: Home Automation
Classifier:   Topic :: Office/Business
Classifier:   Topic :: Software Development :: Libraries :: Application Frameworks
